notion2jekyll/__init__.py
notion2jekyll/__main__.py
notion2jekyll/jekyll_exporter.py
notion2jekyll-0.1.6.dist-info/LICENSE
notion2jekyll-0.1.6.dist-info/METADATA
notion2jekyll-0.1.6.dist-info/WHEEL
notion2jekyll-0.1.6.dist-info/top_level.txt
notion2jekyll-0.1.6.dist-info/RECORD
