Metadata-Version: 2.1
Name: notion2jekyll
Version: 0.1.6
Summary: Export notion page to jekyll post
Home-page: https://github.com/echo724/notion2jekyll.git
Author: Eunchan Cho
Author-email: eunchan1001@gmail.com
License: MIT
Platform: UNKNOWN
Classifier: License :: OSI Approved :: MIT License
Classifier: Operating System :: OS Independent
Classifier: Programming Language :: Python :: 3.7
Requires-Dist: notion (>=0.0.25)
Requires-Dist: requests (>=2.22.0)
Requires-Dist: notion2md (>=0.1.7)
